llmTrace/__init__.py
llmTrace/trace.py
llmtrace_lite-0.0.1.dist-info/METADATA
llmtrace_lite-0.0.1.dist-info/WHEEL
llmtrace_lite-0.0.1.dist-info/top_level.txt
llmtrace_lite-0.0.1.dist-info/RECORD
