Metadata-Version: 2.4
Name: llmtrace-lite
Version: 0.0.1
Summary: Zero-config decorator for tracing LLM calls
Author-email: Your Name <your.email@example.com>
Project-URL: Homepage, https://github.com/yourusername/llmtrace-lite
Classifier: Development Status :: 3 - Alpha
Classifier: Intended Audience :: Developers
Classifier: License :: OSI Approved :: MIT License
Classifier: Programming Language :: Python :: 3
Classifier: Programming Language :: Python :: 3.9
Classifier: Programming Language :: Python :: 3.10
Classifier: Programming Language :: Python :: 3.11
Classifier: Programming Language :: Python :: 3.12
Requires-Python: >=3.9
